setup.py
aryar/__init__.py
aryar/aryar.py
aryar.egg-info/PKG-INFO
aryar.egg-info/SOURCES.txt
aryar.egg-info/dependency_links.txt
aryar.egg-info/requires.txt
aryar.egg-info/top_level.txt