Metadata-Version: 2.1
Name: aryar
Version: 0.1
Requires-Dist: requests
